smiler/__init__.py
smiler/__main__.py
smiler-0.1.3.dist-info/LICENSE
smiler-0.1.3.dist-info/METADATA
smiler-0.1.3.dist-info/WHEEL
smiler-0.1.3.dist-info/entry_points.txt
smiler-0.1.3.dist-info/top_level.txt
smiler-0.1.3.dist-info/zip-safe
smiler-0.1.3.dist-info/RECORD
