Metadata-Version: 2.1
Name: smiler
Version: 0.1.3
Summary: Emoji for humans
Home-page: https://github.com/iyehuda/smiler
Author: Yehuda Chikvashvili
Author-email: yehudaac1@gmail.com
License: UNKNOWN
Keywords: smile,emoji,face
Platform: UNKNOWN
Classifier: Development Status :: 4 - Beta
Classifier: Environment :: Console
Classifier: License :: OSI Approved :: Apache Software License
Classifier: Natural Language :: English
Classifier: Operating System :: OS Independent
Classifier: Programming Language :: Python
